{
    "prepare_queue": {
        "installed": [],
        "uninstalled": []
    },
    "config_munge": {
        "files": {}
    },
    "installed_plugins": {
        "cordova-plugin-battery-status": {
            "PACKAGE_NAME": "com.phonegap.ughealthfinder"
        },
        "cordova-plugin-console": {
            "PACKAGE_NAME": "com.phonegap.ughealthfinder"
        },
        "cordova-plugin-contacts": {
            "PACKAGE_NAME": "com.phonegap.ughealthfinder"
        },
        "cordova-plugin-device": {
            "PACKAGE_NAME": "com.phonegap.ughealthfinder"
        },
        "cordova-plugin-device-motion": {
            "PACKAGE_NAME": "com.phonegap.ughealthfinder"
        }
    },
    "dependent_plugins": {
        "cordova-plugin-compat": {
            "PACKAGE_NAME": "com.phonegap.ughealthfinder"
        }
    }
}